RLPack-1.0.1.data/scripts/simulator
rlpack/__init__.py
rlpack/simulator.py
rlpack/simulator_distributed.py
rlpack/_C/__init__.py
rlpack/_C/grad_accumulator.py
rlpack/_C/memory.py
rlpack/actor_critic/__init__.py
rlpack/actor_critic/a2c.py
rlpack/actor_critic/a3c.py
rlpack/bin/simulator
rlpack/dqn/__init__.py
rlpack/dqn/dqn.py
rlpack/dqn/dqn_agent.py
rlpack/dqn/dqn_proportional_prioritization_agent.py
rlpack/dqn/dqn_rank_based_prioritization_agent.py
rlpack/environments/__init__.py
rlpack/environments/environments.py
rlpack/lib/C_GradAccumulator.cpython-39-darwin.so
rlpack/lib/C_Memory.cpython-39-darwin.so
rlpack/models/__init__.py
rlpack/models/_mlp_feature_extractor.py
rlpack/models/actor_critic_mlp_policy.py
rlpack/models/mlp.py
rlpack/utils/__init__.py
rlpack/utils/internal_code_setup.py
rlpack/utils/normalization.py
rlpack/utils/sanity_check.py
rlpack/utils/setup.py
rlpack/utils/base/__init__.py
rlpack/utils/base/agent.py
rlpack/utils/base/internal_code_register.py
rlpack/utils/base/register.py
RLPack-1.0.1.dist-info/LICENSE.md
RLPack-1.0.1.dist-info/METADATA
RLPack-1.0.1.dist-info/WHEEL
RLPack-1.0.1.dist-info/entry_points.txt
RLPack-1.0.1.dist-info/top_level.txt
RLPack-1.0.1.dist-info/zip-safe
RLPack-1.0.1.dist-info/RECORD
