Metadata-Version: 2.1
Name: RLPack
Version: 1.0.1
Summary: Implementation of RL Algorithms
Home-page: https://github.com/kartik2309/RLPack
Author: Kartik Rajeshwaran
Author-email: kartik.rajeshwaran@gmail.com
License: MIT
Keywords: reinforcement-learning pytorch gym cpp python
Platform: posix
Classifier: Programming Language :: Python :: 3
Classifier: License :: OSI Approved :: MIT License
Classifier: Operating System :: POSIX
Requires-Python: >=3.7
License-File: LICENSE.md
Requires-Dist: numpy (>=1.20.0)
Requires-Dist: gym (>=0.26.0)
Requires-Dist: matplotlib (>=3.4.0)
Requires-Dist: PyYAML (>=6.0)
Requires-Dist: pygame (>=2.1.0)
Requires-Dist: pytest (>=7.0.0)
Requires-Dist: box2d-py (>=2.3.0)
Requires-Dist: torch (>=1.12.0)
Requires-Dist: pybind11 (>=2.10.0)
Provides-Extra: all
Requires-Dist: pytest ; extra == 'all'
Requires-Dist: pytest-icdiff ; extra == 'all'
Provides-Extra: test
Requires-Dist: pytest ; extra == 'test'
Requires-Dist: pytest-icdiff ; extra == 'test'
